.VERSION
AUTHORS.rst
CONTRIBUTING.rst
HISTORY.rst
LICENSE
MANIFEST.in
Pipfile
Pipfile.lock
README.rst
USAGE.rst
dev-requirements.txt
requirements.txt
setup.cfg
setup.py
docs/Makefile
docs/authors.rst
docs/conf.py
docs/contributing.rst
docs/history.rst
docs/index.rst
docs/installation.rst
docs/readme.rst
docs/usage.rst
dummylibrarylib/.VERSION
dummylibrarylib/AUTHORS.rst
dummylibrarylib/CONTRIBUTING.rst
dummylibrarylib/HISTORY.rst
dummylibrarylib/LICENSE
dummylibrarylib/Pipfile
dummylibrarylib/Pipfile.lock
dummylibrarylib/README.rst
dummylibrarylib/USAGE.rst
dummylibrarylib/__init__.py
dummylibrarylib/_version.py
dummylibrarylib/dev-requirements.txt
dummylibrarylib/dummylibrarylib.py
dummylibrarylib/dummylibrarylibexceptions.py
dummylibrarylib/requirements.txt
dummylibrarylib.egg-info/PKG-INFO
dummylibrarylib.egg-info/SOURCES.txt
dummylibrarylib.egg-info/dependency_links.txt
dummylibrarylib.egg-info/not-zip-safe
dummylibrarylib.egg-info/top_level.txt
dummylibrarylib/__pycache__/__init__.cpython-37.pyc
dummylibrarylib/__pycache__/_version.cpython-37.pyc