Metadata-Version: 2.1
Name: dummylibrarylib
Version: 0.1.0
Summary: A template to create python libraries
Home-page: https://github.com/jvilders/Dummy-library.git
Author: Jona Vilders
Author-email: jonavilders@gmail.com
License: MIT
Keywords: dummylibrarylib
Platform: UNKNOWN
Classifier: Development Status :: 1 - Planning
Classifier: Intended Audience :: Developers
Classifier: License :: OSI Approved :: MIT License
Classifier: Natural Language :: English
Classifier: Programming Language :: Python :: 3.7
License-File: LICENSE
License-File: AUTHORS.rst
